{"nodes": [["3", {"node_name": "3", "category": "ports", "type": "1", "bitwidth": "32", "direction": "0", "if_type": "0", "array_size": "0"}], ["12", {"node_name": "12", "category": "nodes", "bitwidth": "32", "opcode": "read", "m_Display": "0", "m_isOnCriticalPath": "0", "m_isStartOfPath": "0", "m_delay": "0.00", "m_topoIndex": "1", "m_isLCDNode": "0", "m_clusterGroupNumber": "-1", "type": "0"}], ["2", {"node_name": "2", "category": "ports", "type": "1", "bitwidth": "8", "direction": "0", "if_type": "0", "array_size": "0"}], ["13", {"node_name": "13", "category": "nodes", "bitwidth": "8", "opcode": "read", "m_Display": "0", "m_isOnCriticalPath": "0", "m_isStartOfPath": "0", "m_delay": "0.00", "m_topoIndex": "2", "m_isLCDNode": "0", "m_clusterGroupNumber": "-1", "type": "0"}], ["14", {"node_name": "14", "category": "nodes", "bitwidth": "32", "opcode": "zext", "m_Display": "0", "m_isOnCriticalPath": "0", "m_isStartOfPath": "0", "m_delay": "0.00", "m_topoIndex": "3", "m_isLCDNode": "0", "m_clusterGroupNumber": "-1", "type": "0"}], ["15", {"node_name": "15", "category": "nodes", "bitwidth": "32", "opcode": "add", "m_Display": "0", "m_isOnCriticalPath": "0", "m_isStartOfPath": "0", "m_delay": "2.55", "m_topoIndex": "4", "m_isLCDNode": "0", "m_clusterGroupNumber": "-1", "type": "0", "const": "42", "const-bitwidth": "32"}], ["23", {"node_name": "23", "category": "blocks", "type": "3"}], ["16", {"node_name": "16", "category": "nodes", "bitwidth": "0", "opcode": "br", "m_Display": "0", "m_isOnCriticalPath": "0", "m_isStartOfPath": "0", "m_delay": "1.58", "m_topoIndex": "5", "m_isLCDNode": "0", "m_clusterGroupNumber": "-1", "type": "0"}], ["18", {"node_name": "18", "category": "nodes", "bitwidth": "32", "opcode": "phi", "m_Display": "0", "m_isOnCriticalPath": "0", "m_isStartOfPath": "0", "m_delay": "0.00", "m_topoIndex": "6", "m_isLCDNode": "0", "m_clusterGroupNumber": "-1", "type": "0"}], ["17", {"node_name": "17", "category": "blocks", "type": "3"}], ["28", {"node_name": "28", "category": "nodes", "bitwidth": "32", "opcode": "zext", "m_Display": "0", "m_isOnCriticalPath": "0", "m_isStartOfPath": "0", "m_delay": "0.00", "m_topoIndex": "13", "m_isLCDNode": "0", "m_clusterGroupNumber": "-1", "type": "0"}], ["30", {"node_name": "30", "category": "blocks", "type": "3"}], ["19", {"node_name": "19", "category": "nodes", "bitwidth": "32", "opcode": "phi", "m_Display": "0", "m_isOnCriticalPath": "0", "m_isStartOfPath": "0", "m_delay": "0.00", "m_topoIndex": "7", "m_isLCDNode": "0", "m_clusterGroupNumber": "-1", "type": "0", "const": "49", "const-bitwidth": "32"}], ["21", {"node_name": "21", "category": "nodes", "bitwidth": "1", "opcode": "icmp", "m_Display": "1", "m_isOnCriticalPath": "0", "m_isStartOfPath": "1", "m_delay": "2.47", "m_topoIndex": "8", "m_isLCDNode": "1", "m_clusterGroupNumber": "-1", "type": "0"}], ["22", {"node_name": "22", "category": "nodes", "bitwidth": "0", "opcode": "br", "m_Display": "0", "m_isOnCriticalPath": "0", "m_isStartOfPath": "0", "m_delay": "0.00", "m_topoIndex": "9", "m_isLCDNode": "0", "m_clusterGroupNumber": "-1", "type": "0"}], ["33", {"node_name": "33", "category": "blocks", "type": "3"}], ["25", {"node_name": "25", "category": "nodes", "bitwidth": "8", "opcode": "udiv", "m_Display": "1", "m_isOnCriticalPath": "0", "m_isStartOfPath": "0", "m_delay": "4.33", "m_topoIndex": "10", "m_isLCDNode": "1", "m_clusterGroupNumber": "-1", "type": "0"}], ["26", {"node_name": "26", "category": "nodes", "bitwidth": "8", "opcode": "trunc", "m_Display": "0", "m_isOnCriticalPath": "0", "m_isStartOfPath": "0", "m_delay": "0.00", "m_topoIndex": "11", "m_isLCDNode": "0", "m_clusterGroupNumber": "-1", "type": "0"}], ["27", {"node_name": "27", "category": "nodes", "bitwidth": "1", "opcode": "icmp", "m_Display": "0", "m_isOnCriticalPath": "0", "m_isStartOfPath": "0", "m_delay": "1.55", "m_topoIndex": "12", "m_isLCDNode": "0", "m_clusterGroupNumber": "-1", "type": "0", "const": "63", "const-bitwidth": "8"}], ["29", {"node_name": "29", "category": "nodes", "bitwidth": "0", "opcode": "br", "m_Display": "0", "m_isOnCriticalPath": "0", "m_isStartOfPath": "0", "m_delay": "0.00", "m_topoIndex": "14", "m_isLCDNode": "0", "m_clusterGroupNumber": "-1", "type": "0"}], ["31", {"node_name": "31", "category": "nodes", "bitwidth": "64", "opcode": "zext", "m_Display": "0", "m_isOnCriticalPath": "0", "m_isStartOfPath": "0", "m_delay": "0.00", "m_topoIndex": "15", "m_isLCDNode": "0", "m_clusterGroupNumber": "-1", "type": "0"}], ["32", {"node_name": "32", "category": "nodes", "bitwidth": "0", "opcode": "ret", "m_Display": "0", "m_isOnCriticalPath": "0", "m_isStartOfPath": "0", "m_delay": "0.00", "m_topoIndex": "16", "m_isLCDNode": "0", "m_clusterGroupNumber": "-1", "type": "0"}]], "edges": [["3", "12", {"edge_name": "36", "is_back_edge": "0", "edge_type": "1"}], ["12", "15", {"edge_name": "41", "is_back_edge": "0", "edge_type": "1"}], ["12", "18", {"edge_name": "45", "is_back_edge": "0", "edge_type": "1"}], ["12", "19", {"edge_name": "52", "is_back_edge": "0", "edge_type": "1"}], ["2", "13", {"edge_name": "39", "is_back_edge": "0", "edge_type": "1"}], ["13", "14", {"edge_name": "40", "is_back_edge": "0", "edge_type": "1"}], ["14", "21", {"edge_name": "54", "is_back_edge": "0", "edge_type": "1"}], ["14", "25", {"edge_name": "59", "is_back_edge": "0", "edge_type": "1"}], ["15", "25", {"edge_name": "60", "is_back_edge": "0", "edge_type": "1"}], ["23", "16", {"edge_name": "44", "is_back_edge": "0", "edge_type": "2"}], ["23", "29", {"edge_name": "66", "is_back_edge": "0", "edge_type": "2"}], ["23", "30", {"edge_name": "159", "is_back_edge": "0", "edge_type": "2"}], ["23", "33", {"edge_name": "160", "is_back_edge": "0", "edge_type": "2"}], ["18", "21", {"edge_name": "55", "is_back_edge": "0", "edge_type": "1"}], ["17", "18", {"edge_name": "46", "is_back_edge": "0", "edge_type": "2"}], ["17", "19", {"edge_name": "51", "is_back_edge": "0", "edge_type": "2"}], ["17", "23", {"edge_name": "158", "is_back_edge": "0", "edge_type": "2"}], ["28", "18", {"edge_name": "47", "is_back_edge": "1", "edge_type": "1"}], ["30", "18", {"edge_name": "48", "is_back_edge": "1", "edge_type": "2"}], ["30", "19", {"edge_name": "53", "is_back_edge": "1", "edge_type": "2"}], ["30", "22", {"edge_name": "58", "is_back_edge": "0", "edge_type": "2"}], ["30", "23", {"edge_name": "161", "is_back_edge": "1", "edge_type": "2"}], ["19", "31", {"edge_name": "67", "is_back_edge": "0", "edge_type": "1"}], ["21", "22", {"edge_name": "56", "is_back_edge": "0", "edge_type": "1"}], ["21", "25", {"edge_name": "2147483647", "is_back_edge": "0", "edge_type": "3"}], ["33", "22", {"edge_name": "57", "is_back_edge": "0", "edge_type": "2"}], ["25", "26", {"edge_name": "61", "is_back_edge": "0", "edge_type": "1"}], ["25", "21", {"edge_name": "2147483647", "is_back_edge": "1", "edge_type": "1"}], ["26", "27", {"edge_name": "62", "is_back_edge": "0", "edge_type": "1"}], ["27", "28", {"edge_name": "65", "is_back_edge": "0", "edge_type": "1"}], ["31", "32", {"edge_name": "68", "is_back_edge": "0", "edge_type": "1"}]]}