<profile>
    <ReportVersion>
        <Version>2020.2</Version>
    </ReportVersion>
    <UserAssignments>
        <unit>ns</unit>
        <ProductFamily>zynq</ProductFamily>
        <Part>xc7z020-clg484-1</Part>
        <TopModelName>fn1</TopModelName>
        <TargetClockPeriod>10.00</TargetClockPeriod>
        <ClockUncertainty>2.70</ClockUncertainty>
        <FlowTarget>vivado</FlowTarget>
    </UserAssignments>
    <PerformanceEstimates>
        <PipelineType>none</PipelineType>
        <SummaryOfTimingAnalysis>
            <unit>ns</unit>
            <EstimatedClockPeriod>4.550</EstimatedClockPeriod>
        </SummaryOfTimingAnalysis>
        <SummaryOfOverallLatency>
            <unit>clock cycles</unit>
            <Best-caseLatency>0</Best-caseLatency>
            <Average-caseLatency>0</Average-caseLatency>
            <Worst-caseLatency>0</Worst-caseLatency>
            <Best-caseRealTimeLatency>0 ns</Best-caseRealTimeLatency>
            <Average-caseRealTimeLatency>0 ns</Average-caseRealTimeLatency>
            <Worst-caseRealTimeLatency>0 ns</Worst-caseRealTimeLatency>
            <Interval-min>1</Interval-min>
            <Interval-max>1</Interval-max>
        </SummaryOfOverallLatency>
    </PerformanceEstimates>
    <AreaEstimates>
        <Resources>
            <FF>0</FF>
            <LUT>75</LUT>
            <BRAM_18K>0</BRAM_18K>
            <DSP>0</DSP>
            <URAM>0</URAM>
        </Resources>
        <AvailableResources>
            <BRAM_18K>280</BRAM_18K>
            <DSP>220</DSP>
            <FF>106400</FF>
            <LUT>53200</LUT>
            <URAM>0</URAM>
        </AvailableResources>
    </AreaEstimates>
    <InterfaceSummary>
        <RtlPorts>
            <name>ap_start</name>
            <Object>fn1</Object>
            <Type>return value</Type>
            <Scope/>
            <IOProtocol>ap_ctrl_hs</IOProtocol>
            <IOConfig/>
            <Dir>in</Dir>
            <Bits>1</Bits>
            <Attribute>control</Attribute>
        </RtlPorts>
        <RtlPorts>
            <name>ap_done</name>
            <Object>fn1</Object>
            <Type>return value</Type>
            <Scope/>
            <IOProtocol>ap_ctrl_hs</IOProtocol>
            <IOConfig/>
            <Dir>out</Dir>
            <Bits>1</Bits>
            <Attribute>control</Attribute>
        </RtlPorts>
        <RtlPorts>
            <name>ap_idle</name>
            <Object>fn1</Object>
            <Type>return value</Type>
            <Scope/>
            <IOProtocol>ap_ctrl_hs</IOProtocol>
            <IOConfig/>
            <Dir>out</Dir>
            <Bits>1</Bits>
            <Attribute>control</Attribute>
        </RtlPorts>
        <RtlPorts>
            <name>ap_ready</name>
            <Object>fn1</Object>
            <Type>return value</Type>
            <Scope/>
            <IOProtocol>ap_ctrl_hs</IOProtocol>
            <IOConfig/>
            <Dir>out</Dir>
            <Bits>1</Bits>
            <Attribute>control</Attribute>
        </RtlPorts>
        <RtlPorts>
            <name>ap_return</name>
            <Object>fn1</Object>
            <Type>return value</Type>
            <Scope/>
            <IOProtocol>ap_ctrl_hs</IOProtocol>
            <IOConfig/>
            <Dir>out</Dir>
            <Bits>16</Bits>
            <Attribute>data</Attribute>
        </RtlPorts>
        <RtlPorts>
            <name>p</name>
            <Object>p</Object>
            <Type>pointer</Type>
            <Scope/>
            <IOProtocol>ap_none</IOProtocol>
            <IOConfig/>
            <Dir>in</Dir>
            <Bits>32</Bits>
            <Attribute>data</Attribute>
            <CType>int</CType>
        </RtlPorts>
        <RtlPorts>
            <name>p_11</name>
            <Object>p_11</Object>
            <Type>pointer</Type>
            <Scope/>
            <IOProtocol>ap_none</IOProtocol>
            <IOConfig/>
            <Dir>in</Dir>
            <Bits>16</Bits>
            <Attribute>data</Attribute>
            <CType>int</CType>
        </RtlPorts>
        <RtlPorts>
            <name>p_13</name>
            <Object>p_13</Object>
            <Type>scalar</Type>
            <Scope/>
            <IOProtocol>ap_none</IOProtocol>
            <IOConfig/>
            <Dir>in</Dir>
            <Bits>32</Bits>
            <Attribute>data</Attribute>
            <CType>int</CType>
        </RtlPorts>
        <RtlPorts>
            <name>p_15</name>
            <Object>p_15</Object>
            <Type>scalar</Type>
            <Scope/>
            <IOProtocol>ap_none</IOProtocol>
            <IOConfig/>
            <Dir>in</Dir>
            <Bits>32</Bits>
            <Attribute>data</Attribute>
            <CType>int</CType>
        </RtlPorts>
        <RtlPorts>
            <name>p_19</name>
            <Object>p_19</Object>
            <Type>scalar</Type>
            <Scope/>
            <IOProtocol>ap_none</IOProtocol>
            <IOConfig/>
            <Dir>in</Dir>
            <Bits>16</Bits>
            <Attribute>data</Attribute>
            <CType>uint</CType>
        </RtlPorts>
    </InterfaceSummary>
    <RTLDesignHierarchy>
        <TopModule>
            <ModuleName>fn1</ModuleName>
        </TopModule>
    </RTLDesignHierarchy>
    <ModuleInformation>
        <Module>
            <Name>fn1</Name>
            <PerformanceEstimates>
                <SummaryOfTimingAnalysis>
                    <TargetClockPeriod>10.00</TargetClockPeriod>
                    <ClockUncertainty>2.70</ClockUncertainty>
                    <EstimatedClockPeriod>4.550</EstimatedClockPeriod>
                </SummaryOfTimingAnalysis>
                <SummaryOfOverallLatency>
                    <Best-caseLatency>0</Best-caseLatency>
                    <Average-caseLatency>0</Average-caseLatency>
                    <Worst-caseLatency>0</Worst-caseLatency>
                    <Best-caseRealTimeLatency>0 ns</Best-caseRealTimeLatency>
                    <Average-caseRealTimeLatency>0 ns</Average-caseRealTimeLatency>
                    <Worst-caseRealTimeLatency>0 ns</Worst-caseRealTimeLatency>
                    <PipelineInitiationInterval>1</PipelineInitiationInterval>
                    <PipelineType>none</PipelineType>
                </SummaryOfOverallLatency>
            </PerformanceEstimates>
            <AreaEstimates>
                <Resources>
                    <FF>0</FF>
                    <AVAIL_FF>106400</AVAIL_FF>
                    <UTIL_FF>0</UTIL_FF>
                    <LUT>75</LUT>
                    <AVAIL_LUT>53200</AVAIL_LUT>
                    <UTIL_LUT>~0</UTIL_LUT>
                    <BRAM_18K>0</BRAM_18K>
                    <AVAIL_BRAM>280</AVAIL_BRAM>
                    <UTIL_BRAM>0</UTIL_BRAM>
                    <DSP>0</DSP>
                    <AVAIL_DSP>220</AVAIL_DSP>
                    <UTIL_DSP>0</UTIL_DSP>
                    <URAM>0</URAM>
                    <AVAIL_URAM>0</AVAIL_URAM>
                    <UTIL_URAM>0</UTIL_URAM>
                </Resources>
            </AreaEstimates>
            <InterfaceSummary>
                <RtlPorts>
                    <name>ap_start</name>
                    <Object>fn1</Object>
                    <Type>return value</Type>
                    <Scope/>
                    <IOProtocol>ap_ctrl_hs</IOProtocol>
                    <IOConfig/>
                    <Dir>in</Dir>
                    <Bits>1</Bits>
                    <Attribute>control</Attribute>
                </RtlPorts>
                <RtlPorts>
                    <name>ap_done</name>
                    <Object>fn1</Object>
                    <Type>return value</Type>
                    <Scope/>
                    <IOProtocol>ap_ctrl_hs</IOProtocol>
                    <IOConfig/>
                    <Dir>out</Dir>
                    <Bits>1</Bits>
                    <Attribute>control</Attribute>
                </RtlPorts>
                <RtlPorts>
                    <name>ap_idle</name>
                    <Object>fn1</Object>
                    <Type>return value</Type>
                    <Scope/>
                    <IOProtocol>ap_ctrl_hs</IOProtocol>
                    <IOConfig/>
                    <Dir>out</Dir>
                    <Bits>1</Bits>
                    <Attribute>control</Attribute>
                </RtlPorts>
                <RtlPorts>
                    <name>ap_ready</name>
                    <Object>fn1</Object>
                    <Type>return value</Type>
                    <Scope/>
                    <IOProtocol>ap_ctrl_hs</IOProtocol>
                    <IOConfig/>
                    <Dir>out</Dir>
                    <Bits>1</Bits>
                    <Attribute>control</Attribute>
                </RtlPorts>
                <RtlPorts>
                    <name>ap_return</name>
                    <Object>fn1</Object>
                    <Type>return value</Type>
                    <Scope/>
                    <IOProtocol>ap_ctrl_hs</IOProtocol>
                    <IOConfig/>
                    <Dir>out</Dir>
                    <Bits>16</Bits>
                    <Attribute>data</Attribute>
                </RtlPorts>
                <RtlPorts>
                    <name>p</name>
                    <Object>p</Object>
                    <Type>pointer</Type>
                    <Scope/>
                    <IOProtocol>ap_none</IOProtocol>
                    <IOConfig/>
                    <Dir>in</Dir>
                    <Bits>32</Bits>
                    <Attribute>data</Attribute>
                    <CType>int</CType>
                </RtlPorts>
                <RtlPorts>
                    <name>p_11</name>
                    <Object>p_11</Object>
                    <Type>pointer</Type>
                    <Scope/>
                    <IOProtocol>ap_none</IOProtocol>
                    <IOConfig/>
                    <Dir>in</Dir>
                    <Bits>16</Bits>
                    <Attribute>data</Attribute>
                    <CType>int</CType>
                </RtlPorts>
                <RtlPorts>
                    <name>p_13</name>
                    <Object>p_13</Object>
                    <Type>scalar</Type>
                    <Scope/>
                    <IOProtocol>ap_none</IOProtocol>
                    <IOConfig/>
                    <Dir>in</Dir>
                    <Bits>32</Bits>
                    <Attribute>data</Attribute>
                    <CType>int</CType>
                </RtlPorts>
                <RtlPorts>
                    <name>p_15</name>
                    <Object>p_15</Object>
                    <Type>scalar</Type>
                    <Scope/>
                    <IOProtocol>ap_none</IOProtocol>
                    <IOConfig/>
                    <Dir>in</Dir>
                    <Bits>32</Bits>
                    <Attribute>data</Attribute>
                    <CType>int</CType>
                </RtlPorts>
                <RtlPorts>
                    <name>p_19</name>
                    <Object>p_19</Object>
                    <Type>scalar</Type>
                    <Scope/>
                    <IOProtocol>ap_none</IOProtocol>
                    <IOConfig/>
                    <Dir>in</Dir>
                    <Bits>16</Bits>
                    <Attribute>data</Attribute>
                    <CType>uint</CType>
                </RtlPorts>
            </InterfaceSummary>
        </Module>
    </ModuleInformation>
    <FIFOInformation/>
    <Args>
        <Arg ArgName="p" index="0" direction="in" srcType="int*" srcSize="32">
            <hwRefs>
                <hwRef type="port" interface="p" name="p" usage="data" direction="in"/>
            </hwRefs>
        </Arg>
        <Arg ArgName="p_11" index="1" direction="unused" srcType="unsigned short*" srcSize="16">
            <hwRefs>
                <hwRef type="port" interface="p_11" name="p_11" usage="data" direction="in"/>
            </hwRefs>
        </Arg>
        <Arg ArgName="p_13" index="2" direction="in" srcType="int" srcSize="32">
            <hwRefs>
                <hwRef type="port" interface="p_13" name="p_13" usage="data" direction="in"/>
            </hwRefs>
        </Arg>
        <Arg ArgName="p_15" index="3" direction="in" srcType="unsigned int" srcSize="32">
            <hwRefs>
                <hwRef type="port" interface="p_15" name="p_15" usage="data" direction="in"/>
            </hwRefs>
        </Arg>
        <Arg ArgName="p_19" index="4" direction="in" srcType="unsigned short" srcSize="16">
            <hwRefs>
                <hwRef type="port" interface="p_19" name="p_19" usage="data" direction="in"/>
            </hwRefs>
        </Arg>
    </Args>
    <ReturnValue ReturnValueName="srcType">short</ReturnValue>
    <ReturnValue ReturnValueName="srcSize">16</ReturnValue>
    <ReturnValue ReturnValueName="hwRefs" type="port" interface="ap_return" name="ap_return" usage="data" direction="out"/>
    <Interfaces>
        <Interface InterfaceName="ap_ctrl" type="ap_ctrl" busTypeName="acc_handshake" mode="slave">
            <portMaps>
                <portMap portMapName="ap_start">start</portMap>
                <portMap portMapName="ap_done">done</portMap>
                <portMap portMapName="ap_idle">idle</portMap>
                <portMap portMapName="ap_ready">ready</portMap>
            </portMaps>
            <ports>
                <port>ap_done</port>
                <port>ap_idle</port>
                <port>ap_ready</port>
                <port>ap_start</port>
            </ports>
        </Interface>
        <Interface InterfaceName="ap_return" type="data" busTypeName="data" mode="master" dataWidth="16">
            <portMaps>
                <portMap portMapName="ap_return">DATA</portMap>
            </portMaps>
            <ports>
                <port>ap_return</port>
            </ports>
        </Interface>
        <Interface InterfaceName="p" type="data" busTypeName="data" mode="slave" dataWidth="32">
            <portMaps>
                <portMap portMapName="p">DATA</portMap>
            </portMaps>
            <ports>
                <port>p</port>
            </ports>
            <constraints>
                <constraint constraint_type="pragma interface" mode="ap_memory" register_option="0" argName="p"/>
            </constraints>
        </Interface>
        <Interface InterfaceName="p_11" type="data" busTypeName="data" mode="slave" dataWidth="16">
            <portMaps>
                <portMap portMapName="p_11">DATA</portMap>
            </portMaps>
            <ports>
                <port>p_11</port>
            </ports>
            <constraints>
                <constraint constraint_type="pragma interface" mode="ap_memory" register_option="0" argName="p_11"/>
            </constraints>
        </Interface>
        <Interface InterfaceName="p_13" type="data" busTypeName="data" mode="slave" dataWidth="32">
            <portMaps>
                <portMap portMapName="p_13">DATA</portMap>
            </portMaps>
            <ports>
                <port>p_13</port>
            </ports>
            <constraints>
                <constraint constraint_type="pragma interface" mode="ap_none" register_option="0" argName="p_13"/>
            </constraints>
        </Interface>
        <Interface InterfaceName="p_15" type="data" busTypeName="data" mode="slave" dataWidth="32">
            <portMaps>
                <portMap portMapName="p_15">DATA</portMap>
            </portMaps>
            <ports>
                <port>p_15</port>
            </ports>
            <constraints>
                <constraint constraint_type="pragma interface" mode="ap_none" register_option="0" argName="p_15"/>
            </constraints>
        </Interface>
        <Interface InterfaceName="p_19" type="data" busTypeName="data" mode="slave" dataWidth="16">
            <portMaps>
                <portMap portMapName="p_19">DATA</portMap>
            </portMaps>
            <ports>
                <port>p_19</port>
            </ports>
            <constraints>
                <constraint constraint_type="pragma interface" mode="ap_none" register_option="0" argName="p_19"/>
            </constraints>
        </Interface>
    </Interfaces>
    <ReportHWInterface>
        <section name="HW Interfaces" level="0">
            <item name="AP_MEMORY">
                <table>
                    <keys size="2">Interface, Bitwidth</keys>
                    <column name="p">32</column>
                    <column name="p_11">16</column>
                </table>
            </item>
            <item name="REGISTER">
                <table>
                    <keys size="3">Interface, Mode, Bitwidth</keys>
                    <column name="ap_return">, 16</column>
                    <column name="p_13">ap_none, 32</column>
                    <column name="p_15">ap_none, 32</column>
                    <column name="p_19">ap_none, 16</column>
                </table>
            </item>
            <item name="TOP LEVEL CONTROL">
                <table>
                    <keys size="3">Interface, Type, Ports</keys>
                    <column name="ap_ctrl">ap_ctrl_hs, ap_done ap_idle ap_ready ap_start</column>
                </table>
            </item>
        </section>
    </ReportHWInterface>
    <ReportSWInterface>
        <section name="SW I/O Information" level="0">
            <item name="Top Function Arguments">
                <table isCollapsed="1">
                    <keys size="3">Argument, Direction, Datatype</keys>
                    <column name="p">in, int*</column>
                    <column name="p_11">unused, unsigned short*</column>
                    <column name="p_13">in, int</column>
                    <column name="p_15">in, unsigned int</column>
                    <column name="p_19">in, unsigned short</column>
                    <column name="return">out, short</column>
                </table>
            </item>
            <item name="SW-to-HW Mapping">
                <table isCollapsed="1">
                    <keys size="3">Argument, HW Name, HW Type</keys>
                    <column name="p">p, port</column>
                    <column name="p_11">p_11, port</column>
                    <column name="p_13">p_13, port</column>
                    <column name="p_15">p_15, port</column>
                    <column name="p_19">p_19, port</column>
                    <column name="return">ap_return, port</column>
                </table>
            </item>
        </section>
    </ReportSWInterface>
    <ReportBurst>
        <section name="M_AXI Burst Information" level="0"/>
    </ReportBurst>
</profile>

